deepsurvk/__init__.py
deepsurvk/cli.py
deepsurvk/deepsurvk.py
deepsurvk/version.py
deepsurvk/applications/recommender.py
deepsurvk/datasets/__init__.py
deepsurvk/network/deepsurvk.py
deepsurvk/network/optimization.py
deepsurvk/network/parameters.py
deepsurvk/utils/concordance.py
deepsurvk/visualization/dsk_metrics.py
deepsurvk/visualization/survival.py
deepsurvk-0.2.2.dist-info/AUTHORS.rst
deepsurvk-0.2.2.dist-info/LICENSE
deepsurvk-0.2.2.dist-info/METADATA
deepsurvk-0.2.2.dist-info/WHEEL
deepsurvk-0.2.2.dist-info/entry_points.txt
deepsurvk-0.2.2.dist-info/top_level.txt
deepsurvk-0.2.2.dist-info/RECORD
