Metadata-Version: 2.1
Name: deepsurvk
Version: 0.2.2
Summary: Implementation of DeepSurv using Keras
Home-page: https://github.com/arturomoncadatorres/deepsurvk
Author: Arturo Moncada-Torres
Author-email: arturomoncadatorres@gmail.com
License: MIT license
Keywords: deepsurvk
Platform: UNKNOWN
Classifier: Development Status :: 4 - Beta
Classifier: Intended Audience :: Developers
Classifier: Intended Audience :: Healthcare Industry
Classifier: License :: OSI Approved :: MIT License
Classifier: Natural Language :: English
Classifier: Programming Language :: Python :: 3
Classifier: Programming Language :: Python :: 3.7
Classifier: Programming Language :: Python :: 3.8
Classifier: Topic :: Scientific/Engineering :: Artificial Intelligence
Classifier: Topic :: Scientific/Engineering :: Medical Science Apps.
Requires-Python: >=3.7
Requires-Dist: tensorflow (>=2.2.0)
Requires-Dist: numpy (==1.18.0)
Requires-Dist: scipy (==1.4.1)
Requires-Dist: scikit-learn (>=0.21.2)
Requires-Dist: pydot (>=1.4.1)
Requires-Dist: graphviz (>=0.14.1)
Requires-Dist: lifelines (>=0.24.15)
Requires-Dist: seaborn (>=0.10.1)
Requires-Dist: pygments (>=2.5.1)
Requires-Dist: h5py (>=2.10.0)
